marceloapd_ic_toolkit/__init__.py
marceloapd_ic_toolkit/database.py
marceloapd_ic_toolkit/functions.py
marceloapd_ic_toolkit/main.py
marceloapd_ic_toolkit-0.4.6.dist-info/entry_points.txt
marceloapd_ic_toolkit-0.4.6.dist-info/WHEEL
marceloapd_ic_toolkit-0.4.6.dist-info/METADATA
marceloapd_ic_toolkit-0.4.6.dist-info/RECORD
